deeplabcut_docker.py
deeplabcut_docker-0.0.10a0.data/data/bin/deeplabcut_docker.sh
deeplabcut_docker-0.0.10a0.dist-info/LICENSE
deeplabcut_docker-0.0.10a0.dist-info/METADATA
deeplabcut_docker-0.0.10a0.dist-info/WHEEL
deeplabcut_docker-0.0.10a0.dist-info/entry_points.txt
deeplabcut_docker-0.0.10a0.dist-info/top_level.txt
deeplabcut_docker-0.0.10a0.dist-info/RECORD
