Metadata-Version: 2.1
Name: deeplabcut-docker
Version: 0.0.10a0
Summary: A helper package to launch DeepLabCut docker images
Home-page: https://github.com/DeepLabCut/DeepLabCut/docker
Author: A. & M. Mathis Labs
Author-email: alexander@deeplabcut.org
Maintainer: Steffen Schneider
Maintainer-email: stes@hey.com
License: LGPLv3
Project-URL: Bug Tracker, https://github.com/DeepLabCut/DeepLabCut/issues
Platform: any
Classifier: Programming Language :: Python :: 3
Classifier: License :: OSI Approved :: GNU Lesser General Public License v3 (LGPLv3)
Classifier: Operating System :: MacOS
Classifier: Operating System :: POSIX :: Linux
Classifier: Topic :: Utilities
Requires-Python: >=3.6
License-File: LICENSE
